highcompress/__init__.py
highcompress/client.py
highcompress/compressed.py
highcompress-3.2.dist-info/METADATA
highcompress-3.2.dist-info/WHEEL
highcompress-3.2.dist-info/top_level.txt
highcompress-3.2.dist-info/RECORD
